setup.py
yorick/__init__.py
yorick/cli.py
yorick/core.py
yorick/renderers.py
yorick.egg-info/PKG-INFO
yorick.egg-info/SOURCES.txt
yorick.egg-info/dependency_links.txt
yorick.egg-info/entry_points.txt
yorick.egg-info/requires.txt
yorick.egg-info/top_level.txt
yorick/closet/example/{project_name}/__init__.py