Metadata-Version: 1.0
Name: yorick
Version: 0.1pre
Summary: a project skeleton / template / boilerplate tool
Home-page: UNKNOWN
Author: Adam Brenecki
Author-email: adam@brenecki.id.au
License: UNKNOWN
Platform: UNKNOWN
